odoo10_addon_product_special_type-10.0.1.0.0.99.dev4-py3.8-nspkg.pth
odoo/addons/product_special_type/README.rst
odoo/addons/product_special_type/__init__.py
odoo/addons/product_special_type/__manifest__.py
odoo/addons/product_special_type/i18n/product_special_type.pot
odoo/addons/product_special_type/models/__init__.py
odoo/addons/product_special_type/models/product_template.py
odoo/addons/product_special_type/readme/CONTRIBUTORS.rst
odoo/addons/product_special_type/readme/DESCRIPTION.rst
odoo/addons/product_special_type/readme/HISTORY.rst
odoo/addons/product_special_type/readme/USAGE.rst
odoo/addons/product_special_type/static/description/icon.png
odoo/addons/product_special_type/static/description/index.html
odoo/addons/product_special_type/views/product_template.xml
odoo10_addon_product_special_type-10.0.1.0.0.99.dev4.dist-info/METADATA
odoo10_addon_product_special_type-10.0.1.0.0.99.dev4.dist-info/WHEEL
odoo10_addon_product_special_type-10.0.1.0.0.99.dev4.dist-info/namespace_packages.txt
odoo10_addon_product_special_type-10.0.1.0.0.99.dev4.dist-info/top_level.txt
odoo10_addon_product_special_type-10.0.1.0.0.99.dev4.dist-info/RECORD
