Metadata-Version: 2.1
Name: odoo10-addon-product-special-type
Version: 10.0.1.0.0.99.dev4
Summary: Add a special type selection on products.
Home-page: https://github.com/OCA/product-attribute
Author: Camptocamp,Odoo Community Association (OCA)
Author-email: support@odoo-community.org
License: AGPL-3
Platform: UNKNOWN
Classifier: Programming Language :: Python
Classifier: Framework :: Odoo
Classifier: Framework :: Odoo :: 10.0
Classifier: License :: OSI Approved :: GNU Affero General Public License v3
Classifier: Development Status :: 4 - Beta
Requires-Python: ~=2.7
Requires-Dist: odoo <10.1dev,>=10.0
